lambda_cloud/__init__.py
lambda_cloud/client.py
lambda_cloud/filesystems.py
lambda_cloud/firewall.py
lambda_cloud/images.py
lambda_cloud/instance_types.py
lambda_cloud/instances.py
lambda_cloud/ssh_keys.py
lambda_cloud/models/__init__.py
lambda_cloud/models/common.py
lambda_cloud/models/error.py
lambda_cloud/models/filesystem.py
lambda_cloud/models/firewall.py
lambda_cloud/models/image.py
lambda_cloud/models/instance.py
lambda_cloud/models/ssh_key.py
lambda_cloud_python-0.0.1.dist-info/licenses/LICENSE
lambda_cloud_python-0.0.1.dist-info/METADATA
lambda_cloud_python-0.0.1.dist-info/WHEEL
lambda_cloud_python-0.0.1.dist-info/top_level.txt
lambda_cloud_python-0.0.1.dist-info/RECORD
