Metadata-Version: 2.4
Name: lambda-cloud-python
Version: 0.0.1
Summary: Python client for Lambda Cloud
Author: Justin Goheen
License:                                  Apache License
Project-URL: Repository, https://github.com/jxtngx/lambda-cloud-python
Classifier: Topic :: Scientific/Engineering :: Artificial Intelligence
Classifier: Operating System :: OS Independent
Classifier: Programming Language :: Python :: 3.11
Requires-Python: >=3.11
License-File: LICENSE
Requires-Dist: httpx
Requires-Dist: pydantic
Provides-Extra: dev
Requires-Dist: ruff; extra == "dev"
Requires-Dist: black; extra == "dev"
Requires-Dist: pytest; extra == "dev"
Requires-Dist: mypy; extra == "dev"
Requires-Dist: coverage; extra == "dev"
Requires-Dist: pre-commit; extra == "dev"
Requires-Dist: isort; extra == "dev"
Provides-Extra: docs
Requires-Dist: mkdocstrings[python]; extra == "docs"
Provides-Extra: packaging
Requires-Dist: setuptools; extra == "packaging"
Requires-Dist: build; extra == "packaging"
Requires-Dist: twine; extra == "packaging"
Dynamic: license-file
